funresource/__init__.py
funresource/run.py
funresource/db/__init__.py
funresource/db/base.py
funresource/generator/__init__.py
funresource/generator/acoooder.py
funresource/generator/base.py
funresource/generator/rss.py
funresource/generator/telegram.py
funresource/view/__init__.py
funresource-1.0.55.dist-info/METADATA
funresource-1.0.55.dist-info/WHEEL
funresource-1.0.55.dist-info/entry_points.txt
funresource-1.0.55.dist-info/top_level.txt
funresource-1.0.55.dist-info/RECORD
